/**********************************************************************
 * Copyright (c) 2005,2006 IBM Corporation and others.
 * All rights reserved.   This program and the accompanying materials
 * are made available under the terms of the Eclipse Public License v1.0
 * which accompanies this distribution, and is available at
 * http://www.eclipse.org/legal/epl-v10.html
 * $Id: JVMIns.def,v 1.8 2006/04/10 03:56:10 gnagarajan Exp $
 * 
 * Contributors: 
 * IBM - Initial API and implementation
 **********************************************************************/

//==============================================================================
// JVMILis.def
//------------------------------------------------------------------------------
// JVM Instructions List
//==============================================================================

//------------------------------------------------------------------------------
//        op  mnemonic       size      arg   net stack  semantic
//------------------------------------------------------------------------------
DEF_JVMI(  0, nop,				1, ARG_NIL	,		 0, SEM_GEN) 
DEF_JVMI(  1, aconst_null,		1, ARG_NIL	,		 1, SEM_GEN) 
DEF_JVMI(  2, iconst_m1,		1, ARG_NIL	,		 1, SEM_GEN) 
DEF_JVMI(  3, iconst_0,			1, ARG_NIL	,		 1, SEM_GEN) 
DEF_JVMI(  4, iconst_1,			1, ARG_NIL	,		 1, SEM_GEN) 
DEF_JVMI(  5, iconst_2,			1, ARG_NIL	,		 1, SEM_GEN) 
DEF_JVMI(  6, iconst_3,			1, ARG_NIL	,		 1, SEM_GEN) 
DEF_JVMI(  7, iconst_4,			1, ARG_NIL	,		 1, SEM_GEN) 
DEF_JVMI(  8, iconst_5,			1, ARG_NIL	,		 1, SEM_GEN) 
DEF_JVMI(  9, lconst_0,			1, ARG_NIL	,		 2, SEM_GEN) 
DEF_JVMI( 10, lconst_1,			1, ARG_NIL	,		 2, SEM_GEN) 
DEF_JVMI( 11, fconst_0,			1, ARG_NIL	,		 1, SEM_GEN) 
DEF_JVMI( 12, fconst_1,			1, ARG_NIL	,		 1, SEM_GEN) 
DEF_JVMI( 13, fconst_2,			1, ARG_NIL	,		 1, SEM_GEN) 
DEF_JVMI( 14, dconst_0,			1, ARG_NIL	,		 2, SEM_GEN) 
DEF_JVMI( 15, dconst_1,			1, ARG_NIL	,		 2, SEM_GEN) 
DEF_JVMI( 16, bipush,			2, ARG_BYTE	,		 1, SEM_GEN) 
DEF_JVMI( 17, sipush,			3, ARG_WORD	,		 1, SEM_GEN)
DEF_JVMI( 18, ldc,				2, ARG_INDB	,		 1, SEM_GEN)
DEF_JVMI( 19, ldc_w,			3, ARG_INDW	,		 1, SEM_GEN)
DEF_JVMI( 20, ldc2_w,			3, ARG_INDW	,		 2, SEM_GEN)
DEF_JVMI( 21, iload,			2, ARG_INDB	,		 1, SEM_GEN)
DEF_JVMI( 22, lload,			2, ARG_INDB	,		 2, SEM_GEN)
DEF_JVMI( 23, fload,			2, ARG_INDB	,		 1, SEM_GEN)
DEF_JVMI( 24, dload,			2, ARG_INDB	,		 2, SEM_GEN)
DEF_JVMI( 25, aload,			2, ARG_INDB	,		 1, SEM_GEN)
DEF_JVMI( 26, iload_0,			1, ARG_NIL	,		 1, SEM_GEN) 
DEF_JVMI( 27, iload_1,			1, ARG_NIL	,		 1, SEM_GEN) 
DEF_JVMI( 28, iload_2,			1, ARG_NIL	,		 1, SEM_GEN) 
DEF_JVMI( 29, iload_3,			1, ARG_NIL	,		 1, SEM_GEN) 
DEF_JVMI( 30, lload_0,			1, ARG_NIL	,		 2, SEM_GEN) 
DEF_JVMI( 31, lload_1,			1, ARG_NIL	,		 2, SEM_GEN) 
DEF_JVMI( 32, lload_2,			1, ARG_NIL	,		 2, SEM_GEN) 
DEF_JVMI( 33, lload_3,			1, ARG_NIL	,		 2, SEM_GEN) 
DEF_JVMI( 34, fload_0,			1, ARG_NIL	,		 1, SEM_GEN) 
DEF_JVMI( 35, fload_1,			1, ARG_NIL	,		 1, SEM_GEN) 
DEF_JVMI( 36, fload_2,			1, ARG_NIL	,		 1, SEM_GEN) 
DEF_JVMI( 37, fload_3,			1, ARG_NIL	,		 1, SEM_GEN) 
DEF_JVMI( 38, dload_0,			1, ARG_NIL	,		 2, SEM_GEN) 
DEF_JVMI( 39, dload_1,			1, ARG_NIL	,		 2, SEM_GEN) 
DEF_JVMI( 40, dload_2,			1, ARG_NIL	,		 2, SEM_GEN) 
DEF_JVMI( 41, dload_3,			1, ARG_NIL	,		 2, SEM_GEN) 
DEF_JVMI( 42, aload_0,			1, ARG_NIL	,		 1, SEM_GEN) 
DEF_JVMI( 43, aload_1,			1, ARG_NIL	,		 1, SEM_GEN) 
DEF_JVMI( 44, aload_2,			1, ARG_NIL	,		 1, SEM_GEN) 
DEF_JVMI( 45, aload_3,			1, ARG_NIL	,		 1, SEM_GEN) 
DEF_JVMI( 46, iaload,			1, ARG_NIL	,		-1, SEM_GEN) 
DEF_JVMI( 47, laload,			1, ARG_NIL	,		 0, SEM_GEN) 
DEF_JVMI( 48, faload,			1, ARG_NIL	,		-1, SEM_GEN) 
DEF_JVMI( 49, daload,			1, ARG_NIL	,		 0, SEM_GEN) 
DEF_JVMI( 50, aaload,			1, ARG_NIL	,		-1, SEM_GEN) 
DEF_JVMI( 51, baload,			1, ARG_NIL	,		-1, SEM_GEN) 
DEF_JVMI( 52, caload,			1, ARG_NIL	,		-1, SEM_GEN) 
DEF_JVMI( 53, saload,			1, ARG_NIL	,		-1, SEM_GEN) 
DEF_JVMI( 54, istore,			2, ARG_INDB	,		-1, SEM_GEN) 
DEF_JVMI( 55, lstore,			2, ARG_INDB	,		-2, SEM_GEN) 
DEF_JVMI( 56, fstore,			2, ARG_INDB	,		-1, SEM_GEN) 
DEF_JVMI( 57, dstore,			2, ARG_INDB	,		-2, SEM_GEN) 
DEF_JVMI( 58, astore,			2, ARG_INDB	,		-1, SEM_GEN) 
DEF_JVMI( 59, istore_0,			1, ARG_NIL	,		-1, SEM_GEN) 
DEF_JVMI( 60, istore_1,			1, ARG_NIL	,		-1, SEM_GEN) 
DEF_JVMI( 61, istore_2,			1, ARG_NIL	,		-1, SEM_GEN) 
DEF_JVMI( 62, istore_3,			1, ARG_NIL	,		-1, SEM_GEN) 
DEF_JVMI( 63, lstore_0,			1, ARG_NIL	,		-2, SEM_GEN) 
DEF_JVMI( 64, lstore_1,			1, ARG_NIL	,		-2, SEM_GEN) 
DEF_JVMI( 65, lstore_2,			1, ARG_NIL	,		-2, SEM_GEN) 
DEF_JVMI( 66, lstore_3,			1, ARG_NIL	,		-2, SEM_GEN) 
DEF_JVMI( 67, fstore_0,			1, ARG_NIL	,		-1, SEM_GEN) 
DEF_JVMI( 68, fstore_1,			1, ARG_NIL	,		-1, SEM_GEN) 
DEF_JVMI( 69, fstore_2,			1, ARG_NIL	,		-1, SEM_GEN) 
DEF_JVMI( 70, fstore_3,			1, ARG_NIL	,		-1, SEM_GEN) 
DEF_JVMI( 71, dstore_0,			1, ARG_NIL	,		-2, SEM_GEN) 
DEF_JVMI( 72, dstore_1,			1, ARG_NIL	,		-2, SEM_GEN) 
DEF_JVMI( 73, dstore_2,			1, ARG_NIL	,		-2, SEM_GEN) 
DEF_JVMI( 74, dstore_3,			1, ARG_NIL	,		-2, SEM_GEN) 
DEF_JVMI( 75, astore_0,			1, ARG_NIL	,		-1, SEM_GEN) 
DEF_JVMI( 76, astore_1,			1, ARG_NIL	,		-1, SEM_GEN) 
DEF_JVMI( 77, astore_2,			1, ARG_NIL	,		-1, SEM_GEN) 
DEF_JVMI( 78, astore_3,			1, ARG_NIL	,		-1, SEM_GEN) 
DEF_JVMI( 79, iastore,			1, ARG_NIL	,		-3, SEM_GEN) 
DEF_JVMI( 80, lastore,			1, ARG_NIL	,		-4, SEM_GEN) 
DEF_JVMI( 81, fastore,			1, ARG_NIL	,		-3, SEM_GEN) 
DEF_JVMI( 82, dastore,			1, ARG_NIL	,		-4, SEM_GEN) 
DEF_JVMI( 83, aastore,			1, ARG_NIL	,		-3, SEM_GEN) 
DEF_JVMI( 84, bastore,			1, ARG_NIL	,		-3, SEM_GEN) 
DEF_JVMI( 85, castore,			1, ARG_NIL	,		-3, SEM_GEN) 
DEF_JVMI( 86, sastore,			1, ARG_NIL	,		-3, SEM_GEN) 
DEF_JVMI( 87, pop,				1, ARG_NIL	,		-1, SEM_GEN) 
DEF_JVMI( 88, pop2,				1, ARG_NIL	,		-2, SEM_GEN) 
DEF_JVMI( 89, dup,				1, ARG_NIL	,		 1, SEM_GEN) 
DEF_JVMI( 90, dup_x1,			1, ARG_NIL	,		 1, SEM_GEN) 
DEF_JVMI( 91, dup_x2,			1, ARG_NIL	,		 1, SEM_GEN) 
DEF_JVMI( 92, dup2,				1, ARG_NIL	,		 2, SEM_GEN) 
DEF_JVMI( 93, dup2_x1,			1, ARG_NIL	,		 2, SEM_GEN) 
DEF_JVMI( 94, dup2_x2,			1, ARG_NIL	,		 2, SEM_GEN) 
DEF_JVMI( 95, swap,				1, ARG_NIL	,		 0, SEM_GEN) 
DEF_JVMI( 96, iadd,				1, ARG_NIL	,		-1, SEM_GEN) 
DEF_JVMI( 97, ladd,				1, ARG_NIL	,		-2, SEM_GEN) 
DEF_JVMI( 98, fadd,				1, ARG_NIL	,		-1, SEM_GEN) 
DEF_JVMI( 99, dadd,				1, ARG_NIL	,		-2, SEM_GEN) 
DEF_JVMI(100, isub,				1, ARG_NIL	,		-1, SEM_GEN) 
DEF_JVMI(101, lsub,				1, ARG_NIL	,		-2, SEM_GEN) 
DEF_JVMI(102, fsub,				1, ARG_NIL	,		-1, SEM_GEN) 
DEF_JVMI(103, dsub,				1, ARG_NIL	,		-2, SEM_GEN) 
DEF_JVMI(104, imul,				1, ARG_NIL	,		-1, SEM_GEN) 
DEF_JVMI(105, lmul,				1, ARG_NIL	,		-2, SEM_GEN) 
DEF_JVMI(106, fmul,				1, ARG_NIL	,		-1, SEM_GEN) 
DEF_JVMI(107, dmul,				1, ARG_NIL	,		-2, SEM_GEN) 
DEF_JVMI(108, idiv,				1, ARG_NIL	,		-1, SEM_GEN) 
DEF_JVMI(109, ldiv,				1, ARG_NIL	,		-2, SEM_GEN) 
DEF_JVMI(110, fdiv,				1, ARG_NIL	,		-1, SEM_GEN) 
DEF_JVMI(111, ddiv,				1, ARG_NIL	,		-2, SEM_GEN) 
DEF_JVMI(112, irem,				1, ARG_NIL	,		-1, SEM_GEN) 
DEF_JVMI(113, lrem,				1, ARG_NIL	,		-2, SEM_GEN) 
DEF_JVMI(114, frem,				1, ARG_NIL	,		-1, SEM_GEN) 
DEF_JVMI(115, drem,				1, ARG_NIL	,		-2, SEM_GEN) 
DEF_JVMI(116, ineg,				1, ARG_NIL	,		 0, SEM_GEN) 
DEF_JVMI(117, lneg,				1, ARG_NIL	,		 0, SEM_GEN) 
DEF_JVMI(118, fneg,				1, ARG_NIL	,		 0, SEM_GEN) 
DEF_JVMI(119, dneg,				1, ARG_NIL	,		 0, SEM_GEN) 
DEF_JVMI(120, ishl,				1, ARG_NIL	,		-1, SEM_GEN) 
DEF_JVMI(121, lshl,				1, ARG_NIL	,		-1, SEM_GEN) 
DEF_JVMI(122, ishr,				1, ARG_NIL	,		-1, SEM_GEN) 
DEF_JVMI(123, lshr,				1, ARG_NIL	,		-1, SEM_GEN) 
DEF_JVMI(124, iushr,			1, ARG_NIL	,		-1, SEM_GEN) 
DEF_JVMI(125, lushr,			1, ARG_NIL	,		-1, SEM_GEN) 
DEF_JVMI(126, iand,				1, ARG_NIL	,		-1, SEM_GEN) 
DEF_JVMI(127, land,				1, ARG_NIL	,		-2, SEM_GEN) 
DEF_JVMI(128, ior,				1, ARG_NIL	,		-1, SEM_GEN) 
DEF_JVMI(129, lor,				1, ARG_NIL	,		-2, SEM_GEN) 
DEF_JVMI(130, ixor,				1, ARG_NIL	,		-1, SEM_GEN) 
DEF_JVMI(131, lxor,				1, ARG_NIL	,		-2, SEM_GEN) 
DEF_JVMI(132, iinc,				3, ARG_NIL	,		 0, SEM_GEN) 
DEF_JVMI(133, i2l,				1, ARG_NIL	,		 1, SEM_GEN) 
DEF_JVMI(134, i2f,				1, ARG_NIL	,		 0, SEM_GEN) 
DEF_JVMI(135, i2d,				1, ARG_NIL	,		 1, SEM_GEN) 
DEF_JVMI(136, l2i,				1, ARG_NIL	,		-1, SEM_GEN) 
DEF_JVMI(137, l2f,				1, ARG_NIL	,		-1, SEM_GEN) 
DEF_JVMI(138, l2d,				1, ARG_NIL	,		 0, SEM_GEN) 
DEF_JVMI(139, f2i,				1, ARG_NIL	,		 0, SEM_GEN) 
DEF_JVMI(140, f2l,				1, ARG_NIL	,		 1, SEM_GEN) 
DEF_JVMI(141, f2d,				1, ARG_NIL	,		 1, SEM_GEN) 
DEF_JVMI(142, d2i,				1, ARG_NIL	,		-1, SEM_GEN) 
DEF_JVMI(143, d2l,				1, ARG_NIL	,		 0, SEM_GEN) 
DEF_JVMI(144, d2f,				1, ARG_NIL	,		-1, SEM_GEN) 
DEF_JVMI(145, i2b,				1, ARG_NIL	,		 0, SEM_GEN) 
DEF_JVMI(146, i2c,				1, ARG_NIL	,		 0, SEM_GEN) 
DEF_JVMI(147, i2s,				1, ARG_NIL	,		 0, SEM_GEN) 
DEF_JVMI(148, lcmp,				1, ARG_NIL	,		-3, SEM_GEN) 
DEF_JVMI(149, fcmpl,			1, ARG_NIL	,		-1, SEM_GEN) 
DEF_JVMI(150, fcmpg,			1, ARG_NIL	,		-1, SEM_GEN) 
DEF_JVMI(151, dcmpl,			1, ARG_NIL	,		-3, SEM_GEN) 
DEF_JVMI(152, dcmpg,			1, ARG_NIL	,		-3, SEM_GEN) 
DEF_JVMI(153, ifeq,				3, ARG_BRW	,		-1, SEM_BRC) 
DEF_JVMI(154, ifne,				3, ARG_BRW	,		-1, SEM_BRC) 
DEF_JVMI(155, iflt,				3, ARG_BRW	,		-1, SEM_BRC) 
DEF_JVMI(156, ifge,				3, ARG_BRW	,		-1, SEM_BRC) 
DEF_JVMI(157, ifgt,				3, ARG_BRW	,		-1, SEM_BRC) 
DEF_JVMI(158, ifle,				3, ARG_BRW	,		-1, SEM_BRC) 
DEF_JVMI(159, if_icmpeq,		3, ARG_BRW	,		-2, SEM_BRC) 
DEF_JVMI(160, if_icmpne,		3, ARG_BRW	,		-2, SEM_BRC) 
DEF_JVMI(161, if_icmplt,		3, ARG_BRW	,		-2, SEM_BRC) 
DEF_JVMI(162, if_icmpge,		3, ARG_BRW	,		-2, SEM_BRC) 
DEF_JVMI(163, if_icmpgt,		3, ARG_BRW	,		-2, SEM_BRC) 
DEF_JVMI(164, if_icmple,		3, ARG_BRW	,		-2, SEM_BRC) 
DEF_JVMI(165, if_acmpeq,		3, ARG_BRW	,		-2, SEM_BRC) 
DEF_JVMI(166, if_acmpne,		3, ARG_BRW	,		-2, SEM_BRC) 
DEF_JVMI(167, goto,				3, ARG_BRW	,		 0, SEM_BR) 
DEF_JVMI(168, jsr,				3, ARG_BRW	,		 0, SEM_JSR)	/* stack +1 in the follow branch */
DEF_JVMI(169, ret,				2, ARG_INDB ,		 0, SEM_RETSR) 
DEF_JVMI(170, tableswitch,	   (unsigned)-1, ARG_NIL	,		-1, SEM_SWITCH) /*special case*/ 
DEF_JVMI(171, lookupswitch,    (unsigned)-1, ARG_NIL	,		-1, SEM_SWITCH) /*special case*/ 
DEF_JVMI(172, ireturn,			1, ARG_NIL	,		-1, SEM_RET) 
DEF_JVMI(173, lreturn,			1, ARG_NIL	,		-2, SEM_RET) 
DEF_JVMI(174, freturn,			1, ARG_NIL	,		-1, SEM_RET) 
DEF_JVMI(175, dreturn,			1, ARG_NIL	,		-2, SEM_RET) 
DEF_JVMI(176, areturn,			1, ARG_NIL	,		-1, SEM_RET) 
DEF_JVMI(177, return,			1, ARG_NIL	,		 0, SEM_RET) 
DEF_JVMI(178, getstatic,		3, ARG_INDW ,/*!*/	 0, SEM_GEN)  /*special case*/
DEF_JVMI(179, putstatic,		3, ARG_INDW	,/*!*/	 0, SEM_GEN)  /*special case*/
DEF_JVMI(180, getfield,			3, ARG_INDW ,/*!*/	 0, SEM_GEN)  /*special case*/
DEF_JVMI(181, putfield,			3, ARG_INDW ,/*!*/	 0, SEM_GEN)  /*special case*/
DEF_JVMI(182, invokevirtual,	3, ARG_INDW ,/*!*/   0, SEM_CALL) /*special case*/
DEF_JVMI(183, invokespecial,	3, ARG_INDW ,/*!*/   0, SEM_CALL) /*special case*/
DEF_JVMI(184, invokestatic,		3, ARG_INDW ,/*!*/   0, SEM_CALL) /*special case*/
DEF_JVMI(185, invokeinterface,  5, ARG_INDW ,/*!*/   0, SEM_CALL) /*special case*/
DEF_JVMI(186, xxxunusedxxx,		1, ARG_NIL	,		 0, SEM_INVALID)
DEF_JVMI(187, new,				3, ARG_INDW ,		 1, SEM_GEN)
DEF_JVMI(188, newarray,			2, ARG_BYTE ,		 0, SEM_GEN)
DEF_JVMI(189, anewarray,		3, ARG_INDW ,		 0, SEM_GEN)
DEF_JVMI(190, arraylength,		1, ARG_NIL	,		 0, SEM_GEN)
DEF_JVMI(191, athrow,		    1, ARG_NIL	,		-1, SEM_THROW)
DEF_JVMI(192, checkcast,		3, ARG_INDW	,		 0, SEM_GEN)
DEF_JVMI(193, instanceof,		3, ARG_INDW	,		 0, SEM_GEN)
DEF_JVMI(194, monitorenter,		1, ARG_NIL	,		-1, SEM_GEN)
DEF_JVMI(195, monitorexit,		1, ARG_NIL	,		-1, SEM_GEN)
DEF_JVMI(196, wide,			   (unsigned)-1, ARG_NIL	,		 0, SEM_GEN) /*special case*/
DEF_JVMI(197, multianewarray,   4, ARG_INDW ,/*!*/   0, SEM_GEN) /*special case*/
DEF_JVMI(198, ifnull,			3, ARG_BRW	,		-1, SEM_BRC)
DEF_JVMI(199, ifnonnull,		3, ARG_BRW	,		-1, SEM_BRC)
DEF_JVMI(200, goto_w,			5, ARG_BRL	,		 0, SEM_BR)
DEF_JVMI(201, jsr_w,			5, ARG_BRL	,		 0, SEM_JSR) /* stack +1 in the follow branch */
// Implement quick opcodes?, 
// Well,  may be... For now just stub them, 
DEF_JVMI(202, ???			,	1, ARG_NIL	,		 0, SEM_INVALID)
DEF_JVMI(203, ???			,	1, ARG_NIL	,		 0, SEM_INVALID)
DEF_JVMI(204, ???			,	1, ARG_NIL	,		 0, SEM_INVALID)
DEF_JVMI(205, ???			,	1, ARG_NIL	,		 0, SEM_INVALID)
DEF_JVMI(206, ???			,	1, ARG_NIL	,		 0, SEM_INVALID)
DEF_JVMI(207, ???			,	1, ARG_NIL	,		 0, SEM_INVALID)
DEF_JVMI(208, ???			,	1, ARG_NIL	,		 0, SEM_INVALID)
DEF_JVMI(209, ???			,	1, ARG_NIL	,		 0, SEM_INVALID)
DEF_JVMI(210, ???			,	1, ARG_NIL	,		 0, SEM_INVALID)
DEF_JVMI(211, ???			,	1, ARG_NIL	,		 0, SEM_INVALID)
DEF_JVMI(212, ???			,	1, ARG_NIL	,		 0, SEM_INVALID)
DEF_JVMI(213, ???			,	1, ARG_NIL	,		 0, SEM_INVALID)
DEF_JVMI(214, ???			,	1, ARG_NIL	,		 0, SEM_INVALID)
DEF_JVMI(215, ???			,	1, ARG_NIL	,		 0, SEM_INVALID)
DEF_JVMI(216, ???			,	1, ARG_NIL	,		 0, SEM_INVALID)
DEF_JVMI(217, ???			,	1, ARG_NIL	,		 0, SEM_INVALID)
DEF_JVMI(218, ???			,	1, ARG_NIL	,		 0, SEM_INVALID)
DEF_JVMI(219, ???			,	1, ARG_NIL	,		 0, SEM_INVALID)
DEF_JVMI(220, ???			,	1, ARG_NIL	,		 0, SEM_INVALID)
DEF_JVMI(221, ???			,	1, ARG_NIL	,		 0, SEM_INVALID)
DEF_JVMI(222, ???			,	1, ARG_NIL	,		 0, SEM_INVALID)
DEF_JVMI(223, ???			,	1, ARG_NIL	,		 0, SEM_INVALID)
DEF_JVMI(224, ???			,	1, ARG_NIL	,		 0, SEM_INVALID)
DEF_JVMI(225, ???			,	1, ARG_NIL	,		 0, SEM_INVALID)
DEF_JVMI(226, ???			,	1, ARG_NIL	,		 0, SEM_INVALID)
DEF_JVMI(227, ???			,	1, ARG_NIL	,		 0, SEM_INVALID)
DEF_JVMI(228, ???			,	1, ARG_NIL	,		 0, SEM_INVALID)
DEF_JVMI(229, ???			,	1, ARG_NIL	,		 0, SEM_INVALID)
DEF_JVMI(230, ???			,	1, ARG_NIL	,		 0, SEM_INVALID)
DEF_JVMI(231, ???			,	1, ARG_NIL	,		 0, SEM_INVALID)
DEF_JVMI(232, ???			,	1, ARG_NIL	,		 0, SEM_INVALID)
DEF_JVMI(233, ???			,	1, ARG_NIL	,		 0, SEM_INVALID)
DEF_JVMI(234, ???			,	1, ARG_NIL	,		 0, SEM_INVALID)
DEF_JVMI(235, ???			,	1, ARG_NIL	,		 0, SEM_INVALID)
DEF_JVMI(236, ???			,	1, ARG_NIL	,		 0, SEM_INVALID)
DEF_JVMI(237, ???			,	1, ARG_NIL	,		 0, SEM_INVALID)
DEF_JVMI(238, ???			,	1, ARG_NIL	,		 0, SEM_INVALID)
DEF_JVMI(239, ???			,	1, ARG_NIL	,		 0, SEM_INVALID)
DEF_JVMI(240, ???			,	1, ARG_NIL	,		 0, SEM_INVALID)
DEF_JVMI(241, ???			,	1, ARG_NIL	,		 0, SEM_INVALID)
DEF_JVMI(242, ???			,	1, ARG_NIL	,		 0, SEM_INVALID)
DEF_JVMI(243, ???			,	1, ARG_NIL	,		 0, SEM_INVALID)
DEF_JVMI(244, ???			,	1, ARG_NIL	,		 0, SEM_INVALID)
DEF_JVMI(245, ???			,	1, ARG_NIL	,		 0, SEM_INVALID)
DEF_JVMI(246, ???			,	1, ARG_NIL	,		 0, SEM_INVALID)
DEF_JVMI(247, ???			,	1, ARG_NIL	,		 0, SEM_INVALID)
DEF_JVMI(248, ???			,	1, ARG_NIL	,		 0, SEM_INVALID)
DEF_JVMI(249, ???			,	1, ARG_NIL	,		 0, SEM_INVALID)
DEF_JVMI(250, ???			,	1, ARG_NIL	,		 0, SEM_INVALID)
DEF_JVMI(251, ???			,	1, ARG_NIL	,		 0, SEM_INVALID)
DEF_JVMI(252, ???			,	1, ARG_NIL	,		 0, SEM_INVALID)
DEF_JVMI(253, ???			,	1, ARG_NIL	,		 0, SEM_INVALID)
DEF_JVMI(254, ???			,	1, ARG_NIL	,		 0, SEM_INVALID)
DEF_JVMI(255, ???			,	1, ARG_NIL	,		 0, SEM_INVALID)

//= End of JVMIList.h ==========================================================
